claude_tmux_hop/__init__.py
claude_tmux_hop/cli.py
claude_tmux_hop/doctor.py
claude_tmux_hop/install.py
claude_tmux_hop/log.py
claude_tmux_hop/parser.py
claude_tmux_hop/paths.py
claude_tmux_hop/priority.py
claude_tmux_hop/testing.py
claude_tmux_hop/tmux.py
claude_tmux_hop/notify/__init__.py
claude_tmux_hop/notify/base.py
claude_tmux_hop/notify/linux.py
claude_tmux_hop/notify/macos.py
claude_tmux_hop/notify/terminals.py
claude_tmux_hop/notify/windows.py
claude_tmux_hop-0.2.5.dist-info/METADATA
claude_tmux_hop-0.2.5.dist-info/WHEEL
claude_tmux_hop-0.2.5.dist-info/entry_points.txt
claude_tmux_hop-0.2.5.dist-info/RECORD
