Metadata-Version: 2.4
Name: claude-tmux-hop
Version: 0.2.5
Summary: Hop between Claude Code sessions in tmux panes
Project-URL: Homepage, https://github.com/unsafe9/claude-tmux-hop
Project-URL: Repository, https://github.com/unsafe9/claude-tmux-hop
Project-URL: Issues, https://github.com/unsafe9/claude-tmux-hop/issues
Author: unsafe9
License-Expression: MIT
Keywords: claude,claude-code,tmux
Classifier: Development Status :: 3 - Alpha
Classifier: Environment :: Console
Classifier: Intended Audience :: Developers
Classifier: License :: OSI Approved :: MIT License
Classifier: Operating System :: POSIX
Classifier: Programming Language :: Python :: 3
Classifier: Programming Language :: Python :: 3.10
Classifier: Programming Language :: Python :: 3.11
Classifier: Programming Language :: Python :: 3.12
Classifier: Programming Language :: Python :: 3.13
Classifier: Topic :: Utilities
Requires-Python: >=3.10
